{
   "abstract" : "Generic interface for Perl5 template engines.",
   "author" : [
      "Tokuhiro Matsuno <tokuhirom AAJKLFJEF@ GMAIL COM>"
   ],
   "dynamic_config" : 0,
   "generated_by" : "Minilla/v0.6.3, CPAN::Meta::Converter version 2.131560",
   "license" : [
      "perl_5"
   ],
   "meta-spec" : {
      "url" : "http://search.cpan.org/perldoc?CPAN::Meta::Spec",
      "version" : "2"
   },
   "name" : "Tiffany",
   "no_index" : {
      "directory" : [
         "t",
         "xt",
         "inc",
         "share",
         "eg",
         "examples",
         "author"
      ]
   },
   "prereqs" : {
      "configure" : {
         "requires" : {
            "CPAN::Meta" : "0",
            "CPAN::Meta::Prereqs" : "0",
            "Module::Build" : "0.38"
         }
      },
      "develop" : {
         "requires" : {
            "Test::CPAN::Meta" : "0",
            "Test::MinimumVersion" : "0.10108",
            "Test::Pod" : "1.41",
            "Test::Spellunker" : "v0.2.7"
         }
      },
      "runtime" : {
         "requires" : {
            "perl" : "5.008001"
         }
      },
      "test" : {
         "requires" : {
            "Test::More" : "0.98",
            "Test::Requires" : "0"
         }
      }
   },
   "release_status" : "unstable",
   "resources" : {
      "bugtracker" : {
         "web" : "https://github.com/tokuhirom/Tiffany/issues"
      },
      "homepage" : "https://github.com/tokuhirom/Tiffany",
      "repository" : {
         "type" : "git",
         "url" : "git://github.com/tokuhirom/Tiffany.git",
         "web" : "https://github.com/tokuhirom/Tiffany"
      }
   },
   "version" : "1.01",
   "x_contributors" : [
      "lestrrat <lestrrat+github@gmail.com>",
      "gfx <gfuji@cpan.org>",
      "tokuhirom <tokuhirom@gmail.com>"
   ]
}
